{
  "immediate": [
    {
      "project_id": "e5f5c55cf91a1f2e1b6ffa65b5ba8ca54014ff1d",
      "name": "Green lotus",
      "city": "Casablanca",
      "zone": "Bouskoura",
      "promoter": null,
      "asset_type": "apartment_3_bed",
      "first_detected_at": "2026-07-15T07:17:40.934361+00:00",
      "last_updated_at": "2026-07-15T07:17:40.934460+00:00",
      "launch_score": 76,
      "confidence_score": 96,
      "investment_score": 89,
      "urgency_score": 86,
      "recommendation": "Buy",
      "status": "urgent",
      "summary": "Green lotus | Promoteur: à confirmer | Ville: Casablanca | Zone: Bouskoura | Confirmations: confirmation en cours | Aucune série de prix fiable pour le moment.",
      "prices": {
        "min": null,
        "max": null
      },
      "aliases": [
        "Green lotus",
        "Green lotus Green lotus Green Lotus"
      ],
      "channels": [
        "advertising"
      ],
      "sources": [
        "Green lotus"
      ],
      "source_urls": [
        "https://www.facebook.com/ads/library/?active_status=active&ad_type=all&country=MA&id=1796362918002528",
        "https://www.facebook.com/ads/library/?active_status=active&ad_type=all&country=MA&id=1039379112368362"
      ],
      "evidence": {
        "signal_count": 2,
        "primary_signal_count": 2,
        "listing_signal_count": 0,
        "source_count": 1,
        "channel_count": 1,
        "primary_channels": [
          "advertising"
        ],
        "secondary_channels": [],
        "confirmations": [],
        "confirmation_details": [],
        "confirmation_count": 0,
        "geo": {
          "lat": 33.5731,
          "lng": -7.5898,
          "sea_distance_km": 6,
          "station_distance_km": 5,
          "highway_distance_km": 4
        },
        "price_band": "unknown",
        "price_evolution": {
          "trend": "unknown",
          "summary": "Aucune série de prix fiable pour le moment."
        },
        "roi": {
          "label": "Élevé",
          "five_year_upside_score": 86
        },
        "project_slug": "green-lotus-e5f5c55c",
        "infrastructure": {
          "sea_distance_km": 6,
          "station_distance_km": 5,
          "highway_distance_km": 4
        },
        "recommendation_narrative": "Acheter rapidement si vérifications terrain confirment le lancement.",
        "source_catalog": [
          {
            "kind": "meta_ads",
            "kind_label": "Publicité Meta",
            "label": "Green lotus · ad #1796362918002528",
            "description": "Publicité Facebook / Instagram repérée via Meta Ad Library.",
            "url": "https://www.facebook.com/ads/library/?active_status=active&ad_type=all&country=MA&id=1796362918002528",
            "source": "Green lotus",
            "signal_type": "meta_ad",
            "proof_level": "direct"
          },
          {
            "kind": "meta_ads",
            "kind_label": "Publicité Meta",
            "label": "Green lotus · ad #1039379112368362",
            "description": "Publicité Facebook / Instagram repérée via Meta Ad Library.",
            "url": "https://www.facebook.com/ads/library/?active_status=active&ad_type=all&country=MA&id=1039379112368362",
            "source": "Green lotus",
            "signal_type": "meta_ad",
            "proof_level": "direct"
          }
        ],
        "practical": {
          "asset_label": "Appartement 3 chambres",
          "public_status": "Aucune disponibilité publique détectée pour le moment.",
          "price_min": null,
          "price_max": null
        },
        "ai_analysis": {
          "summary": "Acheter rapidement si vérifications terrain confirment le lancement.",
          "strengths": [
            "Le score de confiance est élevé, donc le signal paraît crédible.",
            "Le potentiel investissement ressort comme intéressant selon le profil configuré."
          ],
          "risks": [
            "Le prix public n'est pas encore confirmé.",
            "Aucune disponibilité publique confirmée sur portail pour l'instant."
          ],
          "next_steps": [
            "Vérifier le site officiel et les pages sociales du promoteur.",
            "Confirmer les disponibilités et le ticket d'entrée réel.",
            "Surveiller si de nouveaux documents urbanisme ou listings apparaissent."
          ]
        },
        "official_links": [],
        "social_links": [
          {
            "kind": "meta_ads",
            "kind_label": "Publicité Meta",
            "label": "Green lotus · ad #1796362918002528",
            "description": "Publicité Facebook / Instagram repérée via Meta Ad Library.",
            "url": "https://www.facebook.com/ads/library/?active_status=active&ad_type=all&country=MA&id=1796362918002528",
            "source": "Green lotus",
            "signal_type": "meta_ad",
            "proof_level": "direct"
          },
          {
            "kind": "meta_ads",
            "kind_label": "Publicité Meta",
            "label": "Green lotus · ad #1039379112368362",
            "description": "Publicité Facebook / Instagram repérée via Meta Ad Library.",
            "url": "https://www.facebook.com/ads/library/?active_status=active&ad_type=all&country=MA&id=1039379112368362",
            "source": "Green lotus",
            "signal_type": "meta_ad",
            "proof_level": "direct"
          }
        ],
        "listing_links": [],
        "news_links": [],
        "urbanism_links": [],
        "images": [
          "assets/meta/meta-ad-1039379112368362.jpg"
        ],
        "videos": [],
        "changes": [],
        "is_new_project": true
      },
      "reasons": [
        "publicité Meta exacte détectée: ad_id 1796362918002528",
        "type: apartment_3_bed",
        "ville: Casablanca",
        "zone: Bouskoura",
        "publicité Meta exacte détectée: ad_id 1039379112368362"
      ],
      "timeline": [
        {
          "detected_at": "2026-07-15T07:17:40.934361+00:00",
          "channel": "advertising",
          "source": "Green lotus",
          "title": "Green lotus · ad #1796362918002528",
          "url": "https://www.facebook.com/ads/library/?active_status=active&ad_type=all&country=MA&id=1796362918002528"
        },
        {
          "detected_at": "2026-07-15T07:17:40.934460+00:00",
          "channel": "advertising",
          "source": "Green lotus",
          "title": "Green lotus · ad #1039379112368362",
          "url": "https://www.facebook.com/ads/library/?active_status=active&ad_type=all&country=MA&id=1039379112368362"
        }
      ],
      "signals": [
        {
          "collector": "ads.meta_ads",
          "channel": "advertising",
          "source": "Green lotus",
          "signal_type": "meta_ad",
          "title": "Green lotus · ad #1796362918002528",
          "url": "https://www.facebook.com/ads/library/?active_status=active&ad_type=all&country=MA&id=1796362918002528",
          "text": "Green lotus Green lotus Organisé autour d'un parc central privé piéton de près de 9 000 m², Green Lotus Park offre un équilibre parfait entre nature, confort et espace. Appartements 2 & 3 chambres, Duplex Rez-de-jardin et Penthouses en duplex avec piscine. 📍 Nearshore Vallée, Route de Bouskoura, en face du Hilton Garden Inn, Casablanca Learn More ​ https://l.facebook.com/l.php?u=https%3A%2F%2Fgreenlotus.ma%2Fpark%2F&h=AUA-QwU5gYl-jnDEoxjdq6co8AhlOMwN14bBtWEOoOJxwWxEZ3e9JfnczwoblkaN6Qz4MxLwzY_LdfNWylOM5ur-Tt2DZcFrytAO0kBLI58EwSC2tQZUDjAgTpj9yckuCoZpoyp1EQGDVqPV",
          "is_primary": true,
          "launch_weight": 38,
          "confidence_weight": 44,
          "metadata": {
            "promoter_hint": null,
            "ad_id": "1796362918002528",
            "page_name": "Green lotus",
            "ad_snapshot_url": "https://www.facebook.com/ads/library/?active_status=active&ad_type=all&country=MA&id=1796362918002528",
            "landing_page_url": "https://l.facebook.com/l.php?u=https%3A%2F%2Fgreenlotus.ma%2Fpark%2F&h=AUA-QwU5gYl-jnDEoxjdq6co8AhlOMwN14bBtWEOoOJxwWxEZ3e9JfnczwoblkaN6Qz4MxLwzY_LdfNWylOM5ur-Tt2DZcFrytAO0kBLI58EwSC2tQZUDjAgTpj9yckuCoZpoyp1EQGDVqPV",
            "image_urls": [],
            "video_urls": [],
            "query": "Green Lotus",
            "city_hint": "Casablanca",
            "zone_hint": null
          },
          "reasons": [
            "publicité Meta exacte détectée: ad_id 1796362918002528",
            "type: apartment_3_bed",
            "ville: Casablanca",
            "zone: Bouskoura"
          ],
          "discovered_at": "2026-07-15T07:17:40.934361+00:00",
          "city_hint": "Casablanca",
          "zone_hint": "Bouskoura",
          "promoter_hint": null,
          "asset_type_hint": "apartment_3_bed",
          "project_name_hint": "Green lotus",
          "price_mad": null,
          "signal_id": "79899a6cd9824b2a5be9eea405a347e8a3df41db"
        },
        {
          "collector": "ads.meta_ads",
          "channel": "advertising",
          "source": "Green lotus",
          "signal_type": "meta_ad",
          "title": "Green lotus · ad #1039379112368362",
          "url": "https://www.facebook.com/ads/library/?active_status=active&ad_type=all&country=MA&id=1039379112368362",
          "text": "Green lotus Green lotus Green Lotus est un ensemble résidentiel et de services haut standing bénéficiant d’un positionnement exceptionnel à la croisée de 4 pôles clés : Sidi Maarouf, Bouskoura, Californie et Casa Nearshore. Conçu comme un véritable écosystème de vie, où plus des deux tiers du site sont consacrés aux espaces verts et aux aménagements paysagers, le projet est pensé selon une approche durable intégrant des matériaux écoresponsables, une gestion optimisée des ressources et des solutions énergétiques performantes, lui permettant d’obtenir la certification HQE – Haute Qualité Environnementale. Son architecture organique, élégante et contemporaine s’intègre harmonieusement dans son environnement, créant une véritable oasis de sérénité à quelques minutes seulement de l’effervescence urbaine. Green Lotus se positionne comme un nouvel emblème de la vie contemporaine, offrant des perspectives dégagées et un cadre de vie unique dominant l’horizon. Nous rencontrons des problèmes pour lire cette vidéo. En savoir plus La référence du bien-vivre à Casablanca Learn More ​ https://l.facebook.com/l.php?u=https%3A%2F%2Fgreenlotus.ma%2Fpark%2F&h=AUA-QwU5gYl-jnDEoxjdq6co8AhlOMwN14bBtWEOoOJxwWxEZ3e9JfnczwoblkaN6Qz4MxLwzY_LdfNWylOM5ur-Tt2DZcFrytAO0kBLI58EwSC2tQZUDjAgTpj9yckuCoZpoyp1EQGDVqPV",
          "is_primary": true,
          "launch_weight": 38,
          "confidence_weight": 40,
          "metadata": {
            "promoter_hint": null,
            "ad_id": "1039379112368362",
            "page_name": "Green lotus",
            "ad_snapshot_url": "https://www.facebook.com/ads/library/?active_status=active&ad_type=all&country=MA&id=1039379112368362",
            "landing_page_url": "https://l.facebook.com/l.php?u=https%3A%2F%2Fgreenlotus.ma%2Fpark%2F&h=AUA-QwU5gYl-jnDEoxjdq6co8AhlOMwN14bBtWEOoOJxwWxEZ3e9JfnczwoblkaN6Qz4MxLwzY_LdfNWylOM5ur-Tt2DZcFrytAO0kBLI58EwSC2tQZUDjAgTpj9yckuCoZpoyp1EQGDVqPV",
            "image_urls": [],
            "video_urls": [],
            "query": "Green Lotus",
            "city_hint": "Casablanca",
            "zone_hint": null
          },
          "reasons": [
            "publicité Meta exacte détectée: ad_id 1039379112368362",
            "ville: Casablanca",
            "zone: Bouskoura"
          ],
          "discovered_at": "2026-07-15T07:17:40.934460+00:00",
          "city_hint": "Casablanca",
          "zone_hint": "Bouskoura",
          "promoter_hint": null,
          "asset_type_hint": null,
          "project_name_hint": "Green lotus",
          "price_mad": null,
          "signal_id": "bcb9a6c40555ca5947d53ed68bf6dfe87d9a2c60"
        }
      ]
    }
  ],
  "digest": []
}